alpacloud/__init__.py
alpacloud/crdvis/__init__.py
alpacloud/crdvis/crd.py
alpacloud/crdvis/models.py
alpacloud/crdvis/run_app.py
alpacloud/crdvis/vis.py
alpacloud.crdvis-0.1.0.dist-info/METADATA
alpacloud.crdvis-0.1.0.dist-info/WHEEL
alpacloud.crdvis-0.1.0.dist-info/entry_points.txt
alpacloud.crdvis-0.1.0.dist-info/namespace_packages.txt
alpacloud.crdvis-0.1.0.dist-info/top_level.txt
alpacloud.crdvis-0.1.0.dist-info/RECORD
